{
    "Ar36": {
        "error": 0.5819889390921513,
        "error_type": "",
        "fit": "previous",
        "references": [
            {
                "exclude": false,
                "record_id": "ba-03-N-146"
            }
        ],
        "value": 50.920630106501186
    },
    "Ar37": {
        "error": 1.6522619461552856e-06,
        "error_type": "",
        "fit": "previous",
        "references": [
            {
                "exclude": false,
                "record_id": "ba-03-N-146"
            }
        ],
        "value": -6.118864119052935e-07
    },
    "Ar38": {
        "error": 1.8910148528245566e-06,
        "error_type": "",
        "fit": "previous",
        "references": [
            {
                "exclude": false,
                "record_id": "ba-03-N-146"
            }
        ],
        "value": 5.800912437186569e-07
    },
    "Ar39": {
        "error": 4.283443077478675e-07,
        "error_type": "",
        "fit": "previous",
        "references": [
            {
                "exclude": false,
                "record_id": "ba-03-N-146"
            }
        ],
        "value": 2.4037304779607775e-06
    },
    "Ar40": {
        "error": 9.532913475756399e-07,
        "error_type": "",
        "fit": "previous",
        "references": [
            {
                "exclude": false,
                "record_id": "ba-03-N-146"
            }
        ],
        "value": 4.825660617213087e-05
    }
}