{
    "Ar36": {
        "error": 1.7588428354327084,
        "error_type": "",
        "fit": "previous",
        "references": [
            {
                "exclude": false,
                "record_id": "ba-03-N-114"
            }
        ],
        "value": 343.17467247646374
    },
    "Ar37": {
        "error": 3.885418575631381e-06,
        "error_type": "",
        "fit": "previous",
        "references": [
            {
                "exclude": false,
                "record_id": "ba-03-N-114"
            }
        ],
        "value": 1.6980871341698437e-06
    },
    "Ar38": {
        "error": 3.849834681190933e-06,
        "error_type": "",
        "fit": "previous",
        "references": [
            {
                "exclude": false,
                "record_id": "ba-03-N-114"
            }
        ],
        "value": 6.9480324726846045e-06
    },
    "Ar39": {
        "error": 3.443856488279885e-07,
        "error_type": "",
        "fit": "previous",
        "references": [
            {
                "exclude": false,
                "record_id": "ba-03-N-114"
            }
        ],
        "value": 4.6622727048055185e-06
    },
    "Ar40": {
        "error": 3.1438096395181036e-06,
        "error_type": "",
        "fit": "previous",
        "references": [
            {
                "exclude": false,
                "record_id": "ba-03-N-114"
            }
        ],
        "value": 0.0005632215190996884
    }
}