{
    "Ar36": {
        "error": 0.8823469450982296,
        "error_type": "",
        "fit": "previous",
        "references": [
            {
                "exclude": false,
                "record_id": "ba-03-N-325"
            }
        ],
        "value": 118.96873144937388
    },
    "Ar37": {
        "error": 6.071147272408007e-07,
        "error_type": "",
        "fit": "previous",
        "references": [
            {
                "exclude": false,
                "record_id": "ba-03-N-325"
            }
        ],
        "value": 4.607409545390819e-06
    },
    "Ar38": {
        "error": 6.39765828257288e-07,
        "error_type": "",
        "fit": "previous",
        "references": [
            {
                "exclude": false,
                "record_id": "ba-03-N-325"
            }
        ],
        "value": 3.768539540786807e-06
    },
    "Ar39": {
        "error": 4.247671613647139e-07,
        "error_type": "",
        "fit": "previous",
        "references": [
            {
                "exclude": false,
                "record_id": "ba-03-N-325"
            }
        ],
        "value": 2.1568023240068616e-06
    },
    "Ar40": {
        "error": 3.1401731167245167e-06,
        "error_type": "",
        "fit": "previous",
        "references": [
            {
                "exclude": false,
                "record_id": "ba-03-N-325"
            }
        ],
        "value": 6.677980917692327e-05
    }
}