{
    "Ar36": {
        "error": 1.2358914597729398,
        "error_type": "",
        "fit": "previous",
        "references": [
            {
                "exclude": false,
                "record_id": "ba-03-N-390"
            }
        ],
        "value": 105.46592351447809
    },
    "Ar37": {
        "error": 7.430424383421557e-07,
        "error_type": "",
        "fit": "previous",
        "references": [
            {
                "exclude": false,
                "record_id": "ba-03-N-390"
            }
        ],
        "value": 2.121014327924305e-06
    },
    "Ar38": {
        "error": 8.906512923624604e-07,
        "error_type": "",
        "fit": "previous",
        "references": [
            {
                "exclude": false,
                "record_id": "ba-03-N-390"
            }
        ],
        "value": 4.220429245571432e-06
    },
    "Ar39": {
        "error": 3.204695773051671e-07,
        "error_type": "",
        "fit": "previous",
        "references": [
            {
                "exclude": false,
                "record_id": "ba-03-N-390"
            }
        ],
        "value": 3.073081723252676e-06
    },
    "Ar40": {
        "error": 2.0505999259498623e-06,
        "error_type": "",
        "fit": "previous",
        "references": [
            {
                "exclude": false,
                "record_id": "ba-03-N-390"
            }
        ],
        "value": 5.420793284703102e-05
    }
}