{
    "Ar36": {
        "error": 0.9093568313407425,
        "error_type": "",
        "fit": "previous",
        "references": [
            {
                "exclude": false,
                "record_id": "ba-03-N-485"
            }
        ],
        "value": 86.3056472287454
    },
    "Ar37": {
        "error": 9.632748364079115e-07,
        "error_type": "",
        "fit": "previous",
        "references": [
            {
                "exclude": false,
                "record_id": "ba-03-N-485"
            }
        ],
        "value": 3.129143566644931e-07
    },
    "Ar38": {
        "error": 1.1288033590063778e-06,
        "error_type": "",
        "fit": "previous",
        "references": [
            {
                "exclude": false,
                "record_id": "ba-03-N-485"
            }
        ],
        "value": 5.4614109434310994e-06
    },
    "Ar39": {
        "error": 2.6817084897223993e-07,
        "error_type": "",
        "fit": "previous",
        "references": [
            {
                "exclude": false,
                "record_id": "ba-03-N-485"
            }
        ],
        "value": 2.486342742168461e-06
    },
    "Ar40": {
        "error": 1.9352928409461813e-06,
        "error_type": "",
        "fit": "previous",
        "references": [
            {
                "exclude": false,
                "record_id": "ba-03-N-485"
            }
        ],
        "value": 5.146688132080538e-05
    }
}